yaku/autopilot_utils/__init__.py
yaku/autopilot_utils/_version.txt
yaku/autopilot_utils/checks.py
yaku/autopilot_utils/cli_base.py
yaku/autopilot_utils/environment.py
yaku/autopilot_utils/errors.py
yaku/autopilot_utils/results.py
yaku/autopilot_utils/subprocess.py
autopilot_utils-0.1.1.dist-info/METADATA
autopilot_utils-0.1.1.dist-info/WHEEL
autopilot_utils-0.1.1.dist-info/namespace_packages.txt
autopilot_utils-0.1.1.dist-info/top_level.txt
autopilot_utils-0.1.1.dist-info/RECORD
