Metadata-Version: 2.1
Name: autopilot-utils
Version: 0.1.1
Requires-Python: >=3.9
Requires-Dist: click (==8.1.3)
Requires-Dist: datetime
Requires-Dist: loguru (==0.7.0)
Requires-Dist: pydantic (==1.10.13)
Requires-Dist: python-dateutil
Requires-Dist: pytz (==2023.3)
Requires-Dist: types-python-dateutil
Requires-Dist: types-pytz
